vietlott/__init__.py
vietlott/cli/__init__.py
vietlott/cli/crawl.py
vietlott/cli/missing.py
vietlott/config/__init__.py
vietlott/config/map_class.py
vietlott/config/products.py
vietlott/crawler/__init__.py
vietlott/crawler/collections_helper.py
vietlott/crawler/products/__init__.py
vietlott/crawler/products/base.py
vietlott/crawler/products/bingo18.py
vietlott/crawler/products/keno.py
vietlott/crawler/products/p3d.py
vietlott/crawler/products/p3d_pro.py
vietlott/crawler/products/power535.py
vietlott/crawler/products/power645.py
vietlott/crawler/products/power655.py
vietlott/crawler/requests_helper/__init__.py
vietlott/crawler/requests_helper/config.py
vietlott/crawler/requests_helper/fetch.py
vietlott/crawler/schema/__init__.py
vietlott/crawler/schema/requests.py
vietlott/crawler/schema/response.py
vietlott/model/__init__.py
vietlott/model/strategy/__init__.py
vietlott/model/strategy/backtest.py
vietlott/model/strategy/base.py
vietlott/model/strategy/demo.py
vietlott/model/strategy/frequency.py
vietlott/model/strategy/full_test.py
vietlott/model/strategy/not_repeat.py
vietlott/model/strategy/pattern.py
vietlott/model/strategy/random_strategy.py
vietlott/model/strategy/simple_test.py
vietlott/tests/__init__.py
vietlott/tests/config/__init__.py
vietlott/tests/config/test_bingo18.py
vietlott/tests/config/test_power535.py
vietlott/tests/crawler/test_power535.py
vietlott/tests/model/__init__.py
vietlott/tests/model/strategy/__init__.py
vietlott/tests/model/strategy/test_enhanced_backtest.py
vietlott/tests/model/strategy/test_error_handling.py
vietlott/tests/model/strategy/test_validation.py
vietlott/tests/test_crawler/__init__.py
vietlott/tests/test_crawler/test_fetch.py
vietlott/tests/test_crawler/test_power535_schema.py
vietlott/tests/test_crawler/test_schema.py
vietlott_data-0.2.0.dist-info/licenses/LICENSE
vietlott_data-0.2.0.dist-info/METADATA
vietlott_data-0.2.0.dist-info/WHEEL
vietlott_data-0.2.0.dist-info/entry_points.txt
vietlott_data-0.2.0.dist-info/top_level.txt
vietlott_data-0.2.0.dist-info/RECORD
